aploader/__init__.py
aploader/apps.py
aploader/celery.py
aploader/conf.py
aploader/exceptions.py
aploader/signals.py
aploader/urls.py
aploader/admin/__init__.py
aploader/admin/ap_election_meta.py
aploader/bin/deploy.sh
aploader/bin/results.sh
aploader/bin/specials.csv
aploader/management/__init__.py
aploader/management/commands/__init__.py
aploader/management/commands/bootstrap_chamber_calls.py
aploader/management/commands/bootstrap_loader.py
aploader/management/commands/bootstrap_specials.py
aploader/management/commands/get_results.py
aploader/management/commands/initialize_election_date.py
aploader/management/commands/reup_to_db.py
aploader/management/commands/scorecard.py
aploader/management/commands/test_bots.py
aploader/management/commands/utils/__init__.py
aploader/management/commands/utils/notifications/__init__.py
aploader/management/commands/utils/notifications/formatters.py
aploader/migrations/0001_initial.py
aploader/migrations/0002_chambercall.py
aploader/migrations/__init__.py
aploader/models/__init__.py
aploader/models/ap_election_meta.py
aploader/models/chamber_call.py
aploader/serializers/__init__.py
aploader/serializers/ap_election_meta.py
aploader/serializers/chamber_call.py
aploader/static/aploader/css/main-admin-app.css
aploader/static/aploader/js/main-admin-app.js
aploader/tasks/__init__.py
aploader/tasks/bop.py
aploader/tasks/notifications.py
aploader/tasks/slack.py
aploader/tasks/slackchat.py
aploader/tasks/twitter.py
aploader/templates/aploader/base.html
aploader/templates/aploader/caller.html
aploader/utils/__init__.py
aploader/utils/api_auth.py
aploader/utils/auth.py
aploader/utils/aws.py
aploader/utils/importers.py
aploader/views/__init__.py
aploader/views/caller.py
aploader/views/home.py
aploader/viewsets/__init__.py
aploader/viewsets/ap_election_meta.py
aploader/viewsets/base.py
aploader/viewsets/chamber_call.py
politico_civic_ap_loader-0.5.4.dist-info/LICENSE
politico_civic_ap_loader-0.5.4.dist-info/METADATA
politico_civic_ap_loader-0.5.4.dist-info/WHEEL
politico_civic_ap_loader-0.5.4.dist-info/top_level.txt
politico_civic_ap_loader-0.5.4.dist-info/RECORD
